basepair/__init__.py
basepair/api.py
basepair/helpers/__init__.py
basepair/helpers/eprint.py
basepair/helpers/nice_print.py
basepair/helpers/set_filter.py
basepair/infra/__init__.py
basepair/infra/configuration/__init__.py
basepair/infra/configuration/parser.py
basepair/infra/webapp/__init__.py
basepair/infra/webapp/abstract.py
basepair/infra/webapp/analysis.py
basepair/infra/webapp/file.py
basepair/infra/webapp/gene.py
basepair/infra/webapp/genome.py
basepair/infra/webapp/genome_file.py
basepair/infra/webapp/host.py
basepair/infra/webapp/instance.py
basepair/infra/webapp/module.py
basepair/infra/webapp/pipeline.py
basepair/infra/webapp/project.py
basepair/infra/webapp/sample.py
basepair/infra/webapp/upload.py
basepair/infra/webapp/user.py
basepair/modules/__init__.py
basepair/modules/alert/__init__.py
basepair/modules/alert/alert.py
basepair/modules/alert/drivers/__init__.py
basepair/modules/alert/drivers/abstract.py
basepair/modules/alert/drivers/opsgenie.py
basepair/modules/alert/drivers/slack.py
basepair/modules/analysis_log/__init__.py
basepair/modules/analysis_log/abstract.py
basepair/modules/analysis_log/analysis.py
basepair/modules/analysis_log/infra.py
basepair/modules/aws/__init__.py
basepair/modules/aws/cw.py
basepair/modules/aws/ec2.py
basepair/modules/aws/efs.py
basepair/modules/aws/hos.py
basepair/modules/aws/how.py
basepair/modules/aws/iam.py
basepair/modules/aws/instance.py
basepair/modules/aws/logs.py
basepair/modules/aws/mrktpl.py
basepair/modules/aws/policy.py
basepair/modules/aws/s3.py
basepair/modules/aws/service.py
basepair/modules/aws/sm.py
basepair/modules/aws/sqs.py
basepair/modules/aws/sts.py
basepair/modules/aws/swf.py
basepair/modules/aws/handler/__init__.py
basepair/modules/aws/handler/exception.py
basepair/modules/identity/__init__.py
basepair/modules/identity/main.py
basepair/modules/identity/drivers/__init__.py
basepair/modules/identity/drivers/abstract.py
basepair/modules/identity/drivers/aws_iam.py
basepair-2.4.0.dist-info/licenses/LICENSE
basepair-2.4.0.dist-info/licenses/LICENSE.txt
basepair-2.4.0.dist-info/METADATA
basepair-2.4.0.dist-info/WHEEL
basepair-2.4.0.dist-info/top_level.txt
basepair-2.4.0.dist-info/RECORD
