Metadata-Version: 2.4
Name: basepair
Version: 2.4.0
Summary: Python client for Basepair's API
Home-page: https://bitbucket.org/basepair/basepair
Download-URL: https://bitbucket.org/basepair/basepair/get/2.4.0.tar.gz
Author: Basepair
Author-email: info@basepairtech.com
Keywords: bioinformatics,ngs analysis,dna-seq,rna-seq,chip-seq,atac-seq
Classifier: Development Status :: 5 - Production/Stable
Classifier: Intended Audience :: Healthcare Industry
Classifier: Intended Audience :: Science/Research
Classifier: License :: Free for non-commercial use
Classifier: Natural Language :: English
Classifier: Operating System :: OS Independent
Classifier: Programming Language :: Python
Classifier: Programming Language :: Python :: 2.7
Classifier: Programming Language :: Python :: 3.6
Classifier: Topic :: Scientific/Engineering :: Bio-Informatics
License-File: LICENSE
License-File: LICENSE.txt
Requires-Dist: boto3
Requires-Dist: future
Requires-Dist: requests
Requires-Dist: awscli
Requires-Dist: logbook
Requires-Dist: tabulate
Dynamic: author
Dynamic: author-email
Dynamic: classifier
Dynamic: description
Dynamic: description-content-type
Dynamic: download-url
Dynamic: home-page
Dynamic: keywords
Dynamic: license-file
Dynamic: requires-dist
Dynamic: summary
